solve_logic/__init__.py
solve_logic/__main__.py
solve_logic-0.1.6.dist-info/entry_points.txt
solve_logic-0.1.6.dist-info/LICENSE
solve_logic-0.1.6.dist-info/WHEEL
solve_logic-0.1.6.dist-info/METADATA
solve_logic-0.1.6.dist-info/RECORD
