Metadata-Version: 2.1
Name: solve-logic
Version: 0.1.6
Summary: Solve a logic puzzle game.
Home-page: https://github.com/SaitoTsutomu/solve-logic
License: MIT
Author: Saito Tsutomu
Author-email: tsutomu7@hotmail.co.jp
Requires-Python: >=3.9,<4.0
Classifier: Development Status :: 1 - Planning
Classifier: License :: OSI Approved :: MIT License
Classifier: Programming Language :: Python
Classifier: Programming Language :: Python :: 3
Classifier: Programming Language :: Python :: 3.10
Classifier: Programming Language :: Python :: 3.9
Classifier: Topic :: Scientific/Engineering
Classifier: Topic :: Software Development
Requires-Dist: fire (>=0.4.0,<0.5.0)
